assertive/__init__.py
assertive/core.py
assertive/criteria/__init__.py
assertive/criteria/basic.py
assertive/criteria/exception.py
assertive/criteria/list.py
assertive/criteria/mapping.py
assertive/criteria/mock.py
assertive/criteria/numeric.py
assertive/criteria/object.py
assertive/criteria/py.typed
assertive/criteria/string.py
assertive/criteria/utils.py
assertive/py.typed
assertive/serialize.py
assertive-1.2.0.dist-info/LICENSE
assertive-1.2.0.dist-info/METADATA
assertive-1.2.0.dist-info/WHEEL
assertive-1.2.0.dist-info/RECORD
