Metadata-Version: 2.3
Name: assertive
Version: 1.2.0
Summary: A small assertion library for testing
License: MIT
Author: Peter Daly
Requires-Python: >=3.9,<4.0
Classifier: Development Status :: 5 - Production/Stable
Classifier: License :: OSI Approved :: MIT License
Classifier: Programming Language :: Python :: 3
Classifier: Programming Language :: Python :: 3.9
Classifier: Programming Language :: Python :: 3.10
Classifier: Programming Language :: Python :: 3.11
Classifier: Programming Language :: Python :: 3.12
Classifier: Programming Language :: Python :: 3.13
Requires-Dist: bidict (>=0.23.1,<0.24.0)
Project-URL: Documentation, https://peter-daly.github.io/assertive/
Project-URL: Homepage, https://github.com/peter-daly/assertive
Project-URL: Repository, https://github.com/peter-daly/assertive
